fun_with_flags/__init__.py
fun_with_flags/api.py
fun_with_flags/auth.py
fun_with_flags/challenge.py
fun_with_flags/db.py
fun_with_flags/decs.py
fun_with_flags/flags.py
fun_with_flags/helperf.py
fun_with_flags/wsgi.py
fun_with_flags/static/favicon.ico
fun_with_flags/static/style.css
fun_with_flags/templates/base.html
fun_with_flags/templates/index.html
fun_with_flags/templates/auth/authorize.html
fun_with_flags/templates/auth/login.html
fun_with_flags/templates/auth/logout.html
fun_with_flags/templates/challenge/challenge.html
fun_with_flags/templates/challenge/overview.html
fun_with_flags/templates/flags/details.html
fun_with_flags/templates/flags/overview.html
hattrick_fwf-0.2.3.dist-info/METADATA
hattrick_fwf-0.2.3.dist-info/WHEEL
hattrick_fwf-0.2.3.dist-info/licenses/LICENSE
hattrick_fwf-0.2.3.dist-info/RECORD
